tabbit/__init__.py
"tabbit/__init__.py,cover"
tabbit/asgi.py
"tabbit/asgi.py,cover"
tabbit/exceptions.py
tabbit/py.typed
tabbit/config/__init__.py
"tabbit/config/__init__.py,cover"
tabbit/config/logger.py
tabbit/config/settings.py
"tabbit/config/settings.py,cover"
tabbit/database/__init__.py
"tabbit/database/__init__.py,cover"
tabbit/database/models.py
"tabbit/database/models.py,cover"
tabbit/database/session.py
"tabbit/database/session.py,cover"
tabbit/database/operations/__init__.py
"tabbit/database/operations/__init__.py,cover"
tabbit/database/operations/tournament.py
"tabbit/database/operations/tournament.py,cover"
tabbit/routers/__init__.py
"tabbit/routers/__init__.py,cover"
tabbit/routers/enums.py
"tabbit/routers/enums.py,cover"
tabbit/routers/root.py
"tabbit/routers/root.py,cover"
tabbit/routers/util.py
"tabbit/routers/util.py,cover"
tabbit/routers/api/__init__.py
"tabbit/routers/api/__init__.py,cover"
tabbit/routers/api/root.py
"tabbit/routers/api/root.py,cover"
tabbit/routers/api/tournaments.py
"tabbit/routers/api/tournaments.py,cover"
tabbit/schemas/__init__.py
"tabbit/schemas/__init__.py,cover"
tabbit/schemas/enums.py
"tabbit/schemas/enums.py,cover"
tabbit/schemas/root.py
"tabbit/schemas/root.py,cover"
tabbit/schemas/tournament.py
"tabbit/schemas/tournament.py,cover"
tabbit-0.0.0rc1.dist-info/METADATA
tabbit-0.0.0rc1.dist-info/WHEEL
tabbit-0.0.0rc1.dist-info/licenses/LICENSE
tabbit-0.0.0rc1.dist-info/RECORD
